batquant/__init__.py
batquant/vndApi.py
batquant-0.0.4.dist-info/LICENSE
batquant-0.0.4.dist-info/METADATA
batquant-0.0.4.dist-info/WHEEL
batquant-0.0.4.dist-info/top_level.txt
batquant-0.0.4.dist-info/RECORD
