Metadata-Version: 2.1
Name: batquant
Version: 0.0.4
Summary: A package to get Vietnamese stock data
Home-page: https://chulucninh09.visualstudio.com/QuantTrading/_git/batquant
Author: Ninh Chu
Author-email: chulucninh09@gmail.com
License: UNKNOWN
Platform: UNKNOWN
Classifier: Programming Language :: Python :: 3
Classifier: License :: OSI Approved :: MIT License
Classifier: Operating System :: OS Independent
